JOnTADS/JOnTADS.py
JOnTADS/__init__.py
JOnTADS/data_process.py
JOnTADS/dp.py
JOnTADS/get_bds.py
JOnTADS/get_stripe.py
JOnTADS/quant_reg.py
JOnTADS-0.9.dist-info/LICENSE
JOnTADS-0.9.dist-info/METADATA
JOnTADS-0.9.dist-info/WHEEL
JOnTADS-0.9.dist-info/entry_points.txt
JOnTADS-0.9.dist-info/top_level.txt
JOnTADS-0.9.dist-info/RECORD
