Metadata-Version: 2.1
Name: JOnTADS
Version: 0.9
Summary: JOnTADS: a unified caller for TADs and stripes in Hi-C data
Home-page: https://github.com/qunhualilab/JOnTADS
Author: Qiuhai Zeng
Author-email: qiuhai.stat@gmail.com
License: UNKNOWN
Platform: UNKNOWN
Requires-Python: >=3.10.5
License-File: LICENSE
Requires-Dist: numba (==0.56.4)
Requires-Dist: numpy (==1.23.5)
Requires-Dist: scipy (==1.12.0)
Requires-Dist: qpsolvers (==2.7.3)
